elda/__init__.py
elda/main.py
elda/Compiler/__init__.py
elda/Compiler/intermediate_code_generator.py
elda/Compiler/lexer.py
elda/Compiler/parser.py
elda/Compiler/parsetab.py
elda/Compiler/semantic_cube.py
elda/Compiler/vars_table.py
elda/VirtualMachine/__init__.py
elda/VirtualMachine/main_memory.py
elda/VirtualMachine/virtual_machine.py
elda/VirtualMachine/virtual_memory.py
elda-0.1.0.dist-info/LICENSE
elda-0.1.0.dist-info/METADATA
elda-0.1.0.dist-info/WHEEL
elda-0.1.0.dist-info/entry_points.txt
elda-0.1.0.dist-info/top_level.txt
elda-0.1.0.dist-info/RECORD
