Metadata-Version: 2.1
Name: elda
Version: 0.1.0
Summary: A data analysis focused language built with Python
Home-page: https://github.com/Germanvp/ELDA
Author: Juan Manuel Perez & German Villacorta
Author-email: juanmapf97@gmail.com
License: UNKNOWN
Keywords: language data project
Platform: UNKNOWN
Classifier: Programming Language :: Python :: 3.6
Classifier: License :: OSI Approved :: MIT License
Classifier: Operating System :: OS Independent
Requires-Python: >=3
Requires-Dist: ply
Requires-Dist: numpy
Requires-Dist: pandas
Requires-Dist: matplotlib
Requires-Dist: sklearn
